antidotedb/__init__.py
antidotedb/antidoteclient.py
antidotedb/proto/__init__.py
antidotedb/proto/antidote_pb2.py
antidotedb-0.1.3.dist-info/LICENSE
antidotedb-0.1.3.dist-info/METADATA
antidotedb-0.1.3.dist-info/WHEEL
antidotedb-0.1.3.dist-info/top_level.txt
antidotedb-0.1.3.dist-info/RECORD
