Metadata-Version: 2.1
Name: antidotedb
Version: 0.1.3
Summary: AntidoteDB Python clients
Home-page: https://github.com/AntidoteDB/antidote-python-client/tree/master/src/main/python/antidotedb
Author: Nuno Preguica
Author-email: nuno.preguica@fct.unl.pt
License: UNKNOWN
Platform: UNKNOWN
Classifier: Programming Language :: Python :: 3
Classifier: License :: OSI Approved :: Apache Software License
Classifier: Operating System :: OS Independent
Requires-Dist: protobuf
